pypoints2grid-0.2.2.dist-info/METADATA
pypoints2grid-0.2.2.dist-info/RECORD
pypoints2grid-0.2.2.dist-info/WHEEL
pypoints2grid-0.2.2.dist-info/licenses/LICENSE
pypoints2grid/_points2grid.cpython-310-x86_64-linux-gnu.so
pypoints2grid/__init__.py
pypoints2grid.libs/libstdc++-496613c0.so.6.0.32
pypoints2grid.libs/libgcc_s-a3a07607.so.1
