Metadata-Version: 2.1
Name: pypoints2grid
Version: 0.2.2
Summary: implemention of points2grid algorithm
Author-Email: =?utf-8?q?Dag_W=C3=A4stberg?= <dwastberg@gmail.com>
Maintainer-Email: =?utf-8?q?Dag_W=C3=A4stberg?= <dwastberg@gmail.com>
License: BSD-4-Clause
Classifier: Intended Audience :: Science/Research
Classifier: Programming Language :: Python :: 3
Classifier: Programming Language :: C++
Requires-Python: >=3.10
Requires-Dist: numpy>=1.19.2
